py_gql/__init__.py
py_gql/_graphql.py
py_gql/_pkg.py
py_gql/_string_utils.py
py_gql/_utils.py
py_gql/exc.py
py_gql/py.typed
py_gql/tracers.py
py_gql/execution/__init__.py
py_gql/execution/blocking_executor.py
py_gql/execution/default_resolver.py
py_gql/execution/execute.py
py_gql/execution/executor.py
py_gql/execution/get_operation.py
py_gql/execution/instrumentation.py
py_gql/execution/subscribe.py
py_gql/execution/wrappers.py
py_gql/execution/runtime/__init__.py
py_gql/execution/runtime/asyncio.py
py_gql/execution/runtime/base.py
py_gql/execution/runtime/blocking.py
py_gql/execution/runtime/threadpool.py
py_gql/lang/__init__.py
py_gql/lang/ast.py
py_gql/lang/lexer.py
py_gql/lang/parser.py
py_gql/lang/printer.py
py_gql/lang/token.py
py_gql/lang/visitor.py
py_gql/schema/__init__.py
py_gql/schema/_types.py
py_gql/schema/directives.py
py_gql/schema/fix_type_references.py
py_gql/schema/introspection.py
py_gql/schema/resolver_map.py
py_gql/schema/scalars.py
py_gql/schema/schema.py
py_gql/schema/schema_visitor.py
py_gql/schema/types.py
py_gql/schema/validation.py
py_gql/schema/differ/__init__.py
py_gql/schema/differ/changes.py
py_gql/schema/transforms/__init__.py
py_gql/schema/transforms/camel_case.py
py_gql/schema/transforms/visibility.py
py_gql/sdl/__init__.py
py_gql/sdl/ast_schema_printer.py
py_gql/sdl/ast_type_builder.py
py_gql/sdl/schema_directives.py
py_gql/sdl/schema_from_ast.py
py_gql/utilities/__init__.py
py_gql/utilities/ast_node_from_value.py
py_gql/utilities/ast_transforms.py
py_gql/utilities/coerce_value.py
py_gql/utilities/collect_fields.py
py_gql/utilities/introspection_query.py
py_gql/utilities/max_depth.py
py_gql/utilities/untyped_value_from_ast.py
py_gql/utilities/value_from_ast.py
py_gql/validation/__init__.py
py_gql/validation/validate.py
py_gql/validation/visitors.py
py_gql/validation/rules/__init__.py
py_gql/validation/rules/overlapping_fields_can_be_merged.py
py_gql/validation/rules/values_of_correct_type.py
py_gql-0.6.1.dist-info/LICENSE
py_gql-0.6.1.dist-info/METADATA
py_gql-0.6.1.dist-info/WHEEL
py_gql-0.6.1.dist-info/top_level.txt
py_gql-0.6.1.dist-info/RECORD
