Metadata-Version: 2.1
Name: py-gql
Version: 0.6.1
Summary: Comprehensive GraphQL implementation for Python.
Home-page: https://github.com/lirsacc/py-gql
Author: Charles Lirsac
Author-email: c.lirsac@gmail.com
License: MIT
Project-URL: Bug Reports, https://github.com/lirsacc/py-gql/issues
Project-URL: Source, https://github.com/lirsacc/py-gql
Project-URL: Documentation, https://py-gql.readthedocs.io/
Keywords: graphql api
Platform: UNKNOWN
Classifier: License :: OSI Approved :: MIT License
Classifier: Natural Language :: English
Classifier: Programming Language :: Python
Classifier: Programming Language :: Python :: Implementation :: CPython
Classifier: Programming Language :: Python :: Implementation :: PyPy
Classifier: Programming Language :: Python :: 3 :: Only
Classifier: Programming Language :: Python :: 3
Classifier: Programming Language :: Python :: 3.5
Classifier: Programming Language :: Python :: 3.6
Classifier: Programming Language :: Python :: 3.7
Classifier: Programming Language :: Python :: 3.8
Classifier: Operating System :: POSIX
Classifier: Operating System :: MacOS :: MacOS X
Classifier: Development Status :: 4 - Beta
Classifier: Intended Audience :: Developers
Classifier: Topic :: Software Development :: Libraries
Classifier: Topic :: Software Development :: Libraries :: Python Modules
Requires-Python: >=3.5
